setup.py
penlib/__init__.py
penlib/exploitation.py
penlib/postexploitation.py
penlib/reconnaissance.py
penlib.egg-info/PKG-INFO
penlib.egg-info/SOURCES.txt
penlib.egg-info/dependency_links.txt
penlib.egg-info/requires.txt
penlib.egg-info/top_level.txt