Metadata-Version: 1.0
Name: penlib
Version: 0.1.6
Summary: A Python Penetration Package
Home-page: https://github.com/dover247/penlib/
Author: George Sauceda
Author-email: secondclass325@gmail.com
License: UNKNOWN
Platform: UNKNOWN
